16bit_fa.sv
//=========================================================
// 16-bit Full-Adder in SystemVerilog for EE24 Final Project | Sim Target Only
// Implemented with XOR and AND/OR logic only
// Made by: Isaac Medina and Asher Milberg | Tufts University Department of Electrical and Computer Engineering
// Class of 2027
// Date Created: 4/5/2026
//=========================================================

module full_adder (
    input  logic a,
    input  logic b,
    input  logic cin,
    output logic sum,
    output logic cout
);
    assign sum  = a ^ b ^ cin;
    assign cout = (a & b) | (b & cin) | (a & cin);
endmodule

module adder16 (
    input  logic [15:0] A,
    input  logic [15:0] B,
    input  logic        Cin,
    output logic [15:0] Sum,
    output logic        Cout
);
    logic [15:0] carry;

    full_adder fa0 (
        .a    (A[0]),
        .b    (B[0]),
        .cin  (Cin),
        .sum  (Sum[0]),
        .cout (carry[0])
    );

    genvar i;
    generate
        for (i = 1; i < 16; i++) begin : adder_chain
            full_adder fai (
                .a    (A[i]),
                .b    (B[i]),
                .cin  (carry[i-1]),
                .sum  (Sum[i]),
                .cout (carry[i])
            );
        end
    endgenerate

    assign Cout = carry[15];
endmodule

tb.sv
//=========================================================
// 16-bit Full-Adder Testbench in SystemVerilog for EE24 Final Project
// Drives 10,000 random samples, dumps a VCD, and logs a CSV summary.
//=========================================================

`timescale 1ns/1ps

module tb;
    localparam int NUM_SAMPLES = 10000;

    logic [15:0] tb_A;
    logic [15:0] tb_B;
    logic        tb_Cin;
    logic [15:0] dut_Sum;
    logic        dut_Cout;
    logic [16:0] expected_total;

    integer sample_idx;
    integer vector_fd;
    integer results_fd;
    integer scan_count;
    integer loaded_samples;
    integer error_count;
    integer i;
    integer vec_cin_int;
    logic [15:0] vec_A;
    logic [15:0] vec_B;

    adder16 dut (
        .A   (tb_A),
        .B   (tb_B),
        .Cin (tb_Cin),
        .Sum (dut_Sum),
        .Cout(dut_Cout)
    );

    initial begin
        tb_A           = '0;
        tb_B           = '0;
        tb_Cin         = 1'b0;
        expected_total = '0;
        sample_idx     = -1;
        loaded_samples = 0;
        error_count    = 0;

        $dumpfile("adder16_random.vcd");
        $dumpvars(0, tb);

        vector_fd = $fopen("test_vectors.mem", "r");
        if (vector_fd == 0) begin
            $display("ERROR: Could not open test_vectors.mem");
            $finish;
        end

        results_fd = $fopen("simulation_results.csv", "w");
        if (results_fd == 0) begin
            $display("ERROR: Could not open simulation_results.csv for writing");
            $finish;
        end

        $fdisplay(results_fd,
            "sample_idx,time_ns,A_hex,B_hex,Cin,Sum_hex,Cout,Expected_total_hex,Match");

        #1;

        begin : run_vectors
            for (i = 0; i < NUM_SAMPLES; i = i + 1) begin
                scan_count = $fscanf(vector_fd, "%h %h %d\n", vec_A, vec_B, vec_cin_int);
                if (scan_count != 3) begin
                    loaded_samples = i;
                    disable run_vectors;
                end

                sample_idx     = i;
                tb_A           = vec_A;
                tb_B           = vec_B;
                tb_Cin         = vec_cin_int[0];
                expected_total = {1'b0, vec_A} + {1'b0, vec_B} + vec_cin_int[0];
                loaded_samples = i + 1;

                #1;

                if ({dut_Cout, dut_Sum} !== expected_total) begin
                    error_count = error_count + 1;
                    $display(
                        "MISMATCH sample=%0d A=%04h B=%04h Cin=%0d DUT=%05h EXPECTED=%05h",
                        sample_idx,
                        tb_A,
                        tb_B,
                        tb_Cin,
                        {dut_Cout, dut_Sum},
                        expected_total
                    );
                end

                $fdisplay(
                    results_fd,
                    "%0d,%0t,%04h,%04h,%0d,%04h,%0d,%05h,%0d",
                    sample_idx,
                    $time,
                    tb_A,
                    tb_B,
                    tb_Cin,
                    dut_Sum,
                    dut_Cout,
                    expected_total,
                    ({dut_Cout, dut_Sum} === expected_total)
                );

                #9;
            end
        end

        $display("Simulation complete.");
        $display("Loaded samples: %0d", loaded_samples);
        $display("Mismatches: %0d", error_count);

        $fclose(vector_fd);
        $fclose(results_fd);
        $finish;
    end
endmodule

adder16_random.vcd
$date
	Thu Apr 16 19:50:45 2026
$end
$version
	Icarus Verilog
$end
$timescale
	1ps
$end
$scope module tb $end
$var wire 16 ! dut_Sum [15:0] $end
$var wire 1 " dut_Cout $end
$var parameter 32 # NUM_SAMPLES $end
$var reg 17 $ expected_total [16:0] $end
$var reg 16 % tb_A [15:0] $end
$var reg 16 & tb_B [15:0] $end
$var reg 1 ' tb_Cin $end
$var reg 16 ( vec_A [15:0] $end
$var reg 16 ) vec_B [15:0] $end
$var integer 32 * error_count [31:0] $end
$var integer 32 + i [31:0] $end
$var integer 32 , loaded_samples [31:0] $end
$var integer 32 - results_fd [31:0] $end
$var integer 32 . sample_idx [31:0] $end
$var integer 32 / scan_count [31:0] $end
$var integer 32 0 vec_cin_int [31:0] $end
$var integer 32 1 vector_fd [31:0] $end
$scope module dut $end
$var wire 16 2 A [15:0] $end
$var wire 16 3 B [15:0] $end
$var wire 1 ' Cin $end
$var wire 16 4 carry [15:0] $end
$var wire 16 5 Sum [15:0] $end
$var wire 1 " Cout $end
$scope begin adder_chain[1] $end
$var parameter 2 6 i $end
$scope module fai $end
$var wire 1 7 a $end
$var wire 1 8 b $end
$var wire 1 9 cin $end
$var wire 1 : cout $end
$var wire 1 ; sum $end
$upscope $end
$upscope $end
$scope begin adder_chain[2] $end
$var parameter 3 < i $end
$scope module fai $end
$var wire 1 = a $end
$var wire 1 > b $end
$var wire 1 ? cin $end
$var wire 1 @ cout $end
$var wire 1 A sum $end
$upscope $end
$upscope $end
$scope begin adder_chain[3] $end
$var parameter 3 B i $end
$scope module fai $end
$var wire 1 C a $end
$var wire 1 D b $end
$var wire 1 E cin $end
$var wire 1 F cout $end
$var wire 1 G sum $end
$upscope $end
$upscope $end
$scope begin adder_chain[4] $end
$var parameter 4 H i $end
$scope module fai $end
$var wire 1 I a $end
$var wire 1 J b $end
$var wire 1 K cin $end
$var wire 1 L cout $end
$var wire 1 M sum $end
$upscope $end
$upscope $end
$scope begin adder_chain[5] $end
$var parameter 4 N i $end
$scope module fai $end
$var wire 1 O a $end
$var wire 1 P b $end
$var wire 1 Q cin $end
$var wire 1 R cout $end
$var wire 1 S sum $end
$upscope $end
$upscope $end
$scope begin adder_chain[6] $end
$var parameter 4 T i $end
$scope module fai $end
$var wire 1 U a $end
$var wire 1 V b $end
$var wire 1 W cin $end
$var wire 1 X cout $end
$var wire 1 Y sum $end
$upscope $end
$upscope $end
$scope begin adder_chain[7] $end
$var parameter 4 Z i $end
$scope module fai $end
$var wire 1 [ a $end
$var wire 1 \ b $end
$var wire 1 ] cin $end
$var wire 1 ^ cout $end
$var wire 1 _ sum $end
$upscope $end
$upscope $end
$scope begin adder_chain[8] $end
$var parameter 5 ` i $end
$scope module fai $end
$var wire 1 a a $end
$var wire 1 b b $end
$var wire 1 c cin $end
$var wire 1 d cout $end
$var wire 1 e sum $end
$upscope $end
$upscope $end
$scope begin adder_chain[9] $end
$var parameter 5 f i $end
$scope module fai $end
$var wire 1 g a $end
$var wire 1 h b $end
$var wire 1 i cin $end
$var wire 1 j cout $end
$var wire 1 k sum $end
$upscope $end
$upscope $end
$scope begin adder_chain[10] $end
$var parameter 5 l i $end
$scope module fai $end
$var wire 1 m a $end
$var wire 1 n b $end
$var wire 1 o cin $end
$var wire 1 p cout $end
$var wire 1 q sum $end
$upscope $end
$upscope $end
$scope begin adder_chain[11] $end
$var parameter 5 r i $end
$scope module fai $end
$var wire 1 s a $end
$var wire 1 t b $end
$var wire 1 u cin $end
$var wire 1 v cout $end
$var wire 1 w sum $end
$upscope $end
$upscope $end
$scope begin adder_chain[12] $end
$var parameter 5 x i $end
$scope module fai $end
$var wire 1 y a $end
$var wire 1 z b $end
$var wire 1 { cin $end
$var wire 1 | cout $end
$var wire 1 } sum $end
$upscope $end
$upscope $end
$scope begin adder_chain[13] $end
$var parameter 5 ~ i $end
$scope module fai $end
$var wire 1 !" a $end
$var wire 1 "" b $end
$var wire 1 #" cin $end
$var wire 1 $" cout $end
$var wire 1 %" sum $end
$upscope $end
$upscope $end
$scope begin adder_chain[14] $end
$var parameter 5 &" i $end
$scope module fai $end
$var wire 1 '" a $end
$var wire 1 (" b $end
$var wire 1 )" cin $end
$var wire 1 *" cout $end
$var wire 1 +" sum $end
$upscope $end
$upscope $end
$scope begin adder_chain[15] $end
$var parameter 5 ," i $end
$scope module fai $end
$var wire 1 -" a $end
$var wire 1 ." b $end
$var wire 1 /" cin $end
$var wire 1 0" cout $end
$var wire 1 1" sum $end
$upscope $end
$upscope $end
$scope module fa0 $end
$var wire 1 2" a $end
$var wire 1 3" b $end
$var wire 1 ' cin $end
$var wire 1 4" cout $end
$var wire 1 5" sum $end
$upscope $end
$upscope $end
$scope begin run_vectors $end
$upscope $end
$upscope $end
$enddefinitions $end
$comment Show the parameter values. $end
$dumpall
b1111 ,"
b1110 &"
b1101 ~
b1100 x
b1011 r
b1010 l
b1001 f
b1000 `
b111 Z
b110 T
b101 N
b100 H
b11 B
b10 <
b1 6
b10011100010000 #
$end
#0
$dumpvars
05"
04"
03"
02"
01"
00"
0/"
0."
0-"
0+"
0*"
0)"
0("
0'"
0%"
0$"
0#"
0""
0!"
0}
0|
0{
0z
0y
0w
0v
0u
0t
0s
0q
0p
0o
0n
0m
0k
0j
0i
0h
0g
0e
0d
0c
0b
0a
0_
0^
0]
0\
0[
0Y
0X
0W
0V
0U
0S
0R
0Q
0P
0O
0M
0L
0K
0J
0I
0G
0F
0E
0D
0C
0A
0@
0?
0>
0=
0;
0:
09
08
07
b0 5
b0 4
b0 3
b0 2
b10000000000000000000000000000011 1
bx 0
bx /
b11111111111111111111111111111111 .
b10000000000000000000000000000100 -
b0 ,
bx +
b0 *
bx )
bx (
0'
b0 &
b0 %
b0 $
0"
b0 !
$end
#1000
1S
1Q
1L
1K
1F
1E
1q
1@
1o
1j
1?
1:
1Y
1_
1e
1W
1]
1c
1i
19
1R
1X
1^
1d
b1111111111 4
14"
0G
0k
1}
11"
0;
0A
0M
1%"
b1111010111100000 !
b1111010111100000 5
1+"
1D
1P
1V
1\
1b
1h
1z
1."
13"
17
1=
1I
1O
1U
1[
1a
1!"
1'"
12"
b1 ,
b1111010111100000 $
b1001001111101001 &
b1001001111101001 3
b110000111110111 %
b110000111110111 2
b0 .
b11 /
b0 0
b1001001111101001 )
b110000111110111 (
b0 +
#11000
1M
0K
0_
1"
0F
0]
1)"
10"
1G
0X
1{
1$"
0E
1v
0q
01"
0@
0%"
1;
0o
1/"
1A
0S
0W
0i
1#"
09
0j
1*"
0?
0Q
0R
0d
1u
1|
04"
0k
0w
1+"
0:
0L
1Y
b1111110010000000 4
1p
1}
b101000101011111 !
b101000101011111 5
15"
18
0D
1J
0P
0b
0h
1n
1t
1""
1("
03"
07
1C
0I
0O
0U
0a
1m
1y
0!"
02"
b10 ,
b10101000101011111 $
1'
b1111110011010010 &
b1111110011010010 3
b101010010001100 %
b101010010001100 2
b1 .
b1 0
b1111110011010010 )
b101010010001100 (
b1 +
#21000
0o
0#"
1K
0j
0|
0/"
1F
0*"
0G
1E
0i
0{
0)"
0c
0u
1@
0d
0v
0$"
0^
b1000000000001100 4
0p
0A
1M
1e
1k
0w
0%"
1+"
1_
1q
1}
01"
b101011111010011 !
b101011111010011 5
15"
08
1>
0J
0V
1b
1h
0t
0""
0("
13"
17
1U
0[
0m
0y
1-"
b11 ,
b10101011111010011 $
0'
b1001011110000101 &
b1001011110000101 3
b1100000001001110 %
b1100000001001110 2
b10 .
b0 0
b1001011110000101 )
b1100000001001110 (
b10 +
#31000
1A
1i
1?
1W
1d
1:
1R
0e
1w
0E
1c
1o
1u
0"
0;
0@
1Q
1^
1j
1p
00"
19
0G
0}
0M
1L
0S
1Y
0_
1k
1q
1%"
b11110111011 4
14"
b110111001000100 !
b110111001000100 5
05"
18
0>
1D
0b
0z
0."
03"
07
0=
1I
1O
0U
1[
1a
1g
1m
1!"
0-"
12"
b100 ,
b110111001000100 $
1'
b11010001010 &
b11010001010 3
b110011110111001 %
b110011110111001 2
b11 .
b1 0
b11010001010 )
b110011110111001 (
b11 +
#41000
1q
1o
1j
0w
1K
0Y
1_
0u
1}
1F
1E
0W
1]
1i
0p
1{
09
0G
1M
0;
1@
1S
0R
1X
1d
0k
1v
11"
b101111011110 4
04"
b1111010010110100 !
b1111010010110100 5
05"
1>
0D
1J
1V
1b
0n
1t
1""
17
1=
0O
1U
0a
0g
0m
1s
0!"
1-"
02"
b101 ,
b1111010010110100 $
0'
b10101111010110 &
b10101111010110 3
b1100100011011110 %
b1100100011011110 2
b100 .
b0 0
b10101111010110 )
b1100100011011110 (
b100 +
#51000
0Q
0i
0L
0d
0_
1e
1;
1u
0Y
0]
0c
1{
19
1p
0K
0W
0X
0^
1v
1#"
14"
0q
1%"
0A
1G
0F
1M
1S
0R
0k
0w
0}
b1111000000111 4
1|
0+"
b1010000100111010 !
b1010000100111010 5
05"
0V
0\
0b
1n
0""
13"
0=
0C
0I
1O
0U
0[
1a
1g
0s
1y
0'"
b110 ,
b1010000100111010 $
1'
b111000010111 &
b111000010111 3
b1001001100100010 %
b1001001100100010 2
b101 .
b1 0
b111000010111 )
b1001001100100010 (
b101 +
#61000
0{
0v
1w
0u
0p
0;
1q
09
1Q
0o
0%"
1+"
04"
1L
0j
0#"
1)"
1Y
15"
0M
1S
1_
1k
0}
0|
b10000000010110 4
1$"
b100111111101001 !
b100111111101001 5
01"
0>
1V
1b
1""
03"
1=
1I
0O
1[
0a
0g
0y
1!"
0-"
b111 ,
b100111111101001 $
b10111101010010 &
b10111101010010 3
b10000010010110 %
b10000010010110 2
b110 .
b10111101010010 )
b10000010010110 (
b110 +
#71000
1i
1d
0e
1c
1^
0_
1]
1X
0M
01"
0S
1;
0K
0/"
0Q
0Y
0)"
1"
19
0F
0*"
0E
0L
1W
0$"
10"
14"
1G
1k
0q
1}
1+"
1A
0@
b1000000111100011 4
1R
b101101000001110 !
b101101000001110 5
05"
1D
0J
1P
0b
0h
0n
1z
0""
1("
1."
13"
0=
0I
1O
1a
0!"
1-"
12"
b1000 ,
b10101101000001110 $
0'
b1101100001101011 &
b1101100001101011 3
b1000000110100011 %
b1000000110100011 2
b111 .
b0 0
b1101100001101011 )
b1000000110100011 (
b111 +
#81000
1_
0]
0A
0X
0?
0:
1Y
0W
1e
0k
1/"
1"
09
0R
1E
0c
0i
1*"
10"
04"
1;
1G
1S
0}
1@
1M
0^
b1100000000000100 4
0d
1%"
0+"
01"
b10100111111011 !
b10100111111011 5
15"
08
1>
0D
0P
1\
1b
0t
0z
1=
1I
0[
0a
1s
1!"
1'"
0-"
02"
b1001 ,
b10010100111111011 $
b1100000111000101 &
b1100000111000101 3
b110100000110110 %
b110100000110110 2
b1000 .
b1100000111000101 )
b110100000110110 (
b1000 +
#91000
1A
1?
1]
1:
1X
0Y
0G
0;
1W
0E
0/"
19
1R
0@
0*"
b1000000001100011 4
14"
0S
1_
0w
1}
01"
b11000110010100 !
b11000110010100 5
05"
18
0>
1P
0V
0\
1""
0("
07
0=
1U
0s
1y
0!"
0'"
1-"
b1010 ,
b10011000110010100 $
1'
b1010000100100011 &
b1010000100100011 3
b1001000001110000 %
b1001000001110000 2
b1001 .
b1 0
b1010000100100011 )
b1001000001110000 (
b1001 +
#101000
1Q
1L
0A
0?
0M
0:
1K
1F
1;
1W
1#"
0"
09
1R
1|
00"
1E
04"
0S
1Y
1k
1w
0}
1%"
1+"
11"
b1000001111100 4
1@
0G
1q
b1110111111000011 !
b1110111111000011 5
15"
1>
1J
0P
1V
1h
1t
1z
0""
1("
0."
1=
1C
0I
1m
b1011 ,
b1110111111000011 $
0'
b101101101010111 &
b101101101010111 3
b1001010001101100 %
b1001010001101100 2
b1010 .
b0 0
b101101101010111 )
b1001010001101100 (
b1010 +
#111000
1{
1v
0w
1u
1p
0q
1o
1j
0k
1i
1?
0G
1d
1:
1E
1#"
1)"
1"
1Y
0e
0;
1@
1|
1$"
10"
1K
1W
1c
19
0A
0}
0%"
1+"
01"
1F
1M
1R
1^
b1011111111111111 4
14"
b100000011010001 !
b100000011010001 5
15"
08
0>
1D
1P
1\
0b
1n
0z
1""
0("
1."
17
0C
1I
0O
1[
1a
0m
12"
b1100 ,
b10100000011010001 $
1'
b1010111011111001 &
b1010111011111001 3
b1001000111010111 %
b1001000111010111 2
b1011 .
b1 0
b1010111011111001 )
b1001000111010111 (
b1011 +
#121000
0#"
0|
1}
0{
0v
0o
1w
0+"
1e
0j
0u
0)"
0"
0Q
0c
1k
0p
0$"
00"
1E
0L
0^
0i
0Y
0q
0%"
11"
05"
1@
1G
b1001101110011000 !
b1001101110011000 5
0S
b1101111 4
0d
1>
0J
0V
0\
1b
0h
0n
0""
0."
03"
0=
1C
0I
1O
0[
0a
1g
b1101 ,
b1001101110011000 $
b100100101100 &
b100100101100 3
b1001001001101011 %
b1001001001101011 2
b1100 .
b100100101100 )
b1001001001101011 (
b1100 +
#131000
1M
1{
1K
1v
1F
0w
1u
1p
1E
1@
1o
0A
1j
1?
1%"
0k
1:
1#"
1"
0W
1i
0;
1|
10"
0R
1c
1d
19
0Y
1}
01"
0G
1S
0_
1^
1e
0q
b111000100110000 !
b111000100110000 5
1+"
b1001111111001111 4
14"
0>
1V
0t
1z
1."
13"
1=
0C
0O
1[
1a
1m
1s
1'"
02"
b1110 ,
b10111000100110000 $
b1001000101101001 &
b1001000101101001 3
b1101111111000110 %
b1101111111000110 2
b1101 .
b1001000101101001 )
b1101111111000110 (
b1101 +
#141000
01"
0/"
1W
0*"
1R
0#"
1+"
0|
0)"
0S
1]
0"
0$"
0?
1Q
1X
0o
0{
00"
0A
1_
0e
0q
1}
1%"
1;
0:
1L
0Y
1k
0j
b111101010010010 !
b111101010010010 5
1w
b10111111101 4
0v
1>
0D
1J
1\
0b
1n
0z
1""
0."
03"
07
1C
1I
0U
0g
0s
0-"
12"
b1111 ,
b111101010010010 $
b10010011110100 &
b10010011110100 3
b101010110011101 %
b101010110011101 2
b1110 .
b10010011110100 )
b101010110011101 (
b1110 +
#151000
0c
0^
0w
1G
0?
0]
0u
0E
0M
0Q
0:
0X
0p
0@
0K
0L
0i
0o
09
1;
1Y
1q
0%"
11"
1A
0F
0S
1_
0e
0d
1k
0j
0+"
b100000 4
04"
b1001011011001111 !
b1001011011001111 5
15"
18
1D
0J
0V
0n
0""
1."
13"
0=
0C
0I
1O
0[
0a
1g
0'"
02"
b10000 ,
b1001011011001111 $
0'
b1000000010101111 &
b1000000010101111 3
b1011000100000 %
b1011000100000 2
b1111 .
b0 0
b1000000010101111 )
b1011000100000 (
b1111 +
#161000
1E
1@
0A
1+"
0]
1?
0W
1)"
0X
1:
0R
b10000000000110 4
1$"
1G
1Y
0_
0;
0k
b1101000001001001 !
b1101000001001001 5
0q
0D
0P
1V
0\
1""
0."
17
0O
0g
0m
1!"
1-"
b10001 ,
b1101000001001001 $
b10000001000111 &
b10000001000111 3
b1011000000000010 %
b1011000000000010 2
b10000 .
b10000001000111 )
b1011000000000010 (
b10000 +
#171000
1"
1#"
10"
1|
0G
01"
1S
1w
0}
0?
0E
1)"
1/"
1Q
1u
1{
0:
0@
1$"
1*"
1L
1p
b1111110000010000 4
1v
1;
0A
1e
0%"
0+"
05"
b101101100010 !
b101101100010 5
1k
08
0>
1J
1b
1n
1t
0""
1("
03"
1I
1g
1m
1s
b10010 ,
b10000101101100010 $
b100110101010000 &
b100110101010000 3
b1011111000010010 %
b1011111000010010 2
b10001 .
b100110101010000 )
b1011111000010010 (
b10001 +
#181000
0{
0v
1c
1^
1A
0S
1?
0u
0Q
1]
1:
0p
0L
1X
1"
19
1;
1e
1q
0}
1%"
1G
1M
0Y
0_
1w
10"
b1111000011000011 4
14"
b10111100011111 !
b10111100011111 5
15"
18
0b
1h
0n
1z
1""
0("
1."
13"
1C
0I
1U
1[
0g
0s
1'"
0-"
12"
b10011 ,
b10010111100011111 $
1'
b1011101001010011 &
b1011101001010011 3
b111010011001011 %
b111010011001011 2
b10010 .
b1 0
b1011101001010011 )
b111010011001011 (
b10010 +
#191000
0%"
1_
0;
1E
0#"
0]
0e
0)"
09
1@
0|
0X
0c
0$"
04"
0A
0M
0w
1}
0+"
1G
1Y
b1100000000000110 4
0^
0q
b1001011001001 !
b1001011001001 5
15"
1>
0J
1\
0h
0t
0z
0""
1("
0."
03"
0C
0U
0[
1g
0m
0!"
1-"
b10100 ,
b10001001011001001 $
0'
b100000011000110 &
b100000011000110 3
b1101001000000011 %
b1101001000000011 2
b10011 .
b0 0
b100000011000110 )
b1101001000000011 (
b10011 +
#201000
1%"
1#"
1|
0G
0}
1?
0E
1{
1:
0@
1v
0"
19
0;
1A
0Y
1e
1S
0k
11"
00"
b101100000000011 4
14"
b1010000110100101 !
b1010000110100101 5
15"
08
0>
0V
0\
1b
1t
1z
13"
1O
1[
0g
1s
0y
0-"
b10101 ,
b1010000110100101 $
1'
b101100100000001 &
b101100100000001 3
b100100010100011 %
b100100010100011 2
b10100 .
b1 0
b101100100000001 )
b100100010100011 (
b10100 +
#211000
0%"
0#"
0|
1q
1w
1}
01"
1;
0A
1o
1u
0{
1+"
0/"
09
0?
1j
1p
0v
1)"
0*"
1"
04"
0:
1M
1Y
0_
1$"
b1010011000000000 4
10"
b101110101110010 !
b101110101110010 5
05"
18
1P
1h
1n
0t
0z
1""
0("
1."
03"
07
1I
0O
1U
0[
1g
1m
0s
1y
1!"
0'"
1-"
02"
b10110 ,
b10101110101110010 $
0'
b1010011100100010 &
b1010011100100010 3
b1011011001010000 %
b1011011001010000 2
b10101 .
b0 0
b1010011100100010 )
b1011011001010000 (
b10101 +
#221000
1%"
1#"
1|
11"
0q
0w
1/"
1W
0o
0u
0}
1*"
1R
0j
0p
1{
0;
1A
1G
0+"
15"
0S
1Y
b1010000111011101 !
b1010000111011101 5
1_
b1111100000100000 4
1v
08
1>
1D
0h
0n
1t
1z
1("
13"
1O
0U
1[
0g
0m
1s
0y
b10111 ,
b11010000111011101 $
b1111100100101101 &
b1111100100101101 3
b1010100010110000 %
b1010100010110000 2
b10110 .
b1111100100101101 )
b1010100010110000 (
b10110 +
#231000
1k
1i
0%"
1d
0#"
0|
0e
1c
1}
1^
1Q
1W
0{
0_
0"
1L
1R
0v
1]
00"
1;
0A
0M
0S
1q
1w
05"
0Y
b110000111110000 4
1X
b1101111000001010 !
b1101111000001010 5
1+"
18
0>
1J
0P
1n
0t
0."
03"
1U
1'"
0-"
b11000 ,
b1101111000001010 $
b111010100011010 &
b111010100011010 3
b110100011110000 %
b110100011110000 2
b10111 .
b111010100011010 )
b110100011110000 (
b10111 +
#241000
0]
0k
1S
0X
0+"
0i
0Q
1Y
0)"
0d
0L
0W
0$"
1"
0G
0_
1e
0R
1%"
01"
b1100000010000000 4
10"
b11110101100011 !
b11110101100011 5
15"
0D
0J
1P
1\
0b
0I
0O
0!"
1-"
b11001 ,
b10011110101100011 $
1'
b111010010100010 &
b111010010100010 3
b1100100011000000 %
b1100100011000000 2
b11000 .
b1 0
b111010010100010 )
b1100100011000000 (
b11000 +
#251000
1u
1p
0q
1o
1j
0e
1+"
0c
1)"
0^
1i
1$"
19
1;
0k
11"
1A
1d
1w
0%"
b1101100001100110 !
b1101100001100110 5
05"
b1110011100000001 4
14"
08
0P
0\
1b
1h
0z
1."
1=
1O
0[
1a
0s
1y
1!"
12"
b11010 ,
b11101100001100110 $
b1110011100000000 &
b1110011100000000 3
b1111000101100101 %
b1111000101100101 2
b11001 .
b1110011100000000 )
b1111000101100101 (
b11001 +
#261000
0+"
0o
0i
0)"
0j
0d
b1100010000000001 4
0$"
1G
1_
0k
15"
0A
0q
1%"
b11100011101011 !
b11100011101011 5
01"
1D
1P
1V
1\
0b
0h
1z
13"
0=
0O
0U
0a
1m
0y
0!"
0-"
b11011 ,
b10011100011101011 $
b1111010011101001 &
b1111010011101001 3
b100010000000001 %
b100010000000001 2
b11010 .
b1111010011101001 )
b100010000000001 (
b11010 +
#271000
1W
1R
0S
1Q
1L
1e
1q
0"
1K
1c
1o
00"
1F
1^
1j
0A
0G
0_
11"
0?
1{
1E
1]
1i
0/"
09
0:
1v
1@
1X
1d
0*"
b111111111100 4
04"
1;
0M
0w
1}
0%"
1Y
0k
b1101010101000011 !
b1101010101000011 5
1+"
18
1>
0D
1J
0P
0\
1b
1t
0z
0""
03"
1=
1C
1O
1U
1[
1a
1g
0'"
02"
b11100 ,
b1101010101000011 $
b1100110101010110 &
b1100110101010110 3
b11111101100 %
b11111101100 2
b11011 .
b1100110101010110 )
b11111101100 (
b11011 +
#281000
0u
0p
0o
0j
0G
1k
1?
1E
0i
1%"
1:
1@
1K
0d
1#"
19
1q
0+"
1;
0A
1F
1M
0Y
0w
b1010011100010011 !
b1010011100010011 5
0}
1|
b1100011111111 4
14"
1D
0b
0n
0("
0."
13"
17
0=
0C
1I
0U
0a
1s
1y
1-"
12"
b11101 ,
b1010011100010011 $
b100001011111 &
b100001011111 3
b1001111010110011 %
b1001111010110011 2
b11100 .
b100001011111 )
b1001111010110011 (
b11100 +
#291000
0w
0c
0u
0^
0p
1_
1q
0]
0o
0X
0j
1S
1"
0Q
1Y
1k
1%"
10"
0L
0W
0i
1#"
01"
0;
1A
0R
1e
0d
b1001100000001111 4
1|
1+"
b110011111110100 !
b110011111110100 5
05"
0D
0J
1P
1h
1z
1."
07
1=
1C
0I
0O
1a
0g
0y
1'"
b11110 ,
b10110011111110100 $
0'
b1001101001100111 &
b1001101001100111 3
b1100110110001101 %
b1100110110001101 2
b11101 .
b0 0
b1001101001100111 )
b1100110110001101 (
b11101 +
#301000
1/"
1*"
1W
1R
0+"
1)"
0S
1o
1"
1$"
1Q
1j
10"
1Y
0%"
b1111101000111111 4
1L
0_
0k
1q
1}
01"
b1010101010101 !
b1010101010101 5
15"
1J
0V
1b
1""
1("
1I
0[
0a
1g
0m
1y
0'"
0-"
b11111 ,
b10001010101010101 $
1'
b1111101100110111 &
b1111101100110111 3
b1101000011101 %
b1101000011101 2
b11110 .
b1 0
b1111101100110111 )
b1101000011101 (
b11110 +
#311000
1c
1^
0"
00"
1w
11"
1]
1u
0)"
0/"
1X
1p
0$"
b1111011111111 4
0*"
1G
0M
0Y
0_
1e
0q
0}
1%"
0+"
1;
b1010100100001110 !
b1010100100001110 5
05"
1D
0J
1V
1\
0b
1n
0z
0""
0("
0."
17
1-"
b100000 ,
b1010100100001110 $
0'
b111011101111 &
b111011101111 3
b1001101000011111 %
b1001101000011111 2
b11111 .
b0 0
b111011101111 )
b1001101000011111 (
b11111 +
#321000
1#"
1|
0}
1{
1v
1u
0Q
1/"
1p
0L
1*"
0e
0q
0A
0G
1M
0c
1o
1"
0?
0E
0K
0^
1j
10"
0:
0@
0F
1i
1)"
1_
0k
0+"
11"
0S
1d
0w
0%"
b1111111101100001 4
1$"
b1000000010010010 !
b1000000010010010 5
05"
08
0>
0D
0V
0\
1b
0h
0n
1("
1."
07
0=
0C
1O
1U
1a
1m
0s
1!"
02"
b100001 ,
b11000000010010010 $
1'
b1100100100100001 &
b1100100100100001 3
b1011011101110000 %
b1011011101110000 2
b100000 .
b1 0
b1100100100100001 )
b1011011101110000 (
b100000 +
#331000
1K
1F
0q
1o
1E
1j
01"
1@
0k
0/"
0W
0_
1i
0"
0*"
1?
0R
0]
1c
1d
1u
0#"
0)"
00"
0G
0+"
1:
0A
1M
1S
0Y
0X
1^
0e
1p
1w
1}
0|
b1100000110010 !
b1100000110010 5
0%"
b111110001111 4
0$"
18
1D
1\
1n
0("
0."
03"
17
1=
0I
0O
0U
1[
0a
0m
1s
0y
0!"
0-"
12"
b100010 ,
b1100000110010 $
b110110101010 &
b110110101010 3
b101010000111 %
b101010000111 2
b100001 .
b110110101010 )
b101010000111 (
b100001 +
#341000
1_
1]
0}
1X
0{
0i
0v
0M
1W
0d
1?
0K
1R
1:
0F
1e
0u
1G
0S
0c
0p
0E
1Q
0^
0o
19
0q
0;
1A
0@
1L
0Y
0k
0j
1w
1%"
11"
b1110011 4
14"
b1010100110001100 !
b1010100110001100 5
05"
0D
1J
0\
0n
13"
07
0=
1C
1I
1U
0[
0g
0s
1!"
1-"
b100011 ,
b1010100110001100 $
0'
b100100110011 &
b100100110011 3
b1010000001011001 %
b1010000001011001 2
b100010 .
b0 0
b100100110011 )
b1010000001011001 (
b100010 +
#351000
1Y
1k
1E
1K
1Q
0W
0c
1i
1u
1#"
1/"
1@
1F
1L
0R
0^
0]
1d
1p
1|
1*"
0A
1G
0M
1S
1_
1w
b101010100011111 4
0X
0e
1%"
11"
b1010101011101000 !
b1010101011101000 5
05"
1>
1D
0J
0P
1V
1\
1n
0t
1z
1("
0U
1a
1m
1y
0!"
1'"
0-"
02"
b100100 ,
b1010101011101000 $
1'
b101010111001111 &
b101010111001111 3
b101010100011000 %
b101010100011000 2
b100011 .
b1 0
b101010111001111 )
b101010100011000 (
b100011 +
#361000
0?
0:
0G
0q
0w
0%"
01"
1;
0E
0W
0o
0K
0i
0u
0#"
1+"
0/"
09
0@
0R
0j
0F
0Q
0d
0p
0|
1)"
0*"
04"
0A
1S
0Y
1k
0M
0L
1}
b10000000000000 4
1$"
b101001010100011 !
b101001010100011 5
15"
08
0>
0D
1P
0V
0b
1h
0n
1""
0("
03"
17
0C
0I
0a
0m
0y
1!"
0'"
12"
b100101 ,
b101001010100011 $
0'
b11001010100000 &
b11001010100000 3
b10000000000011 %
b10000000000011 2
b100100 .
b0 0
b11001010100000 )
b10000000000011 (
b100100 +
